ediko/__init__.py
ediko-0.0.3.dist-info/METADATA
ediko-0.0.3.dist-info/WHEEL
ediko-0.0.3.dist-info/top_level.txt
ediko-0.0.3.dist-info/RECORD
