Metadata-Version: 2.4
Name: ediko
Version: 0.0.3
Summary: package ediko nian
Author: Noro18
License: MIT
